meros/__init__.py
meros/meros.py
meros-0.1.0.dist-info/LICENSE
meros-0.1.0.dist-info/METADATA
meros-0.1.0.dist-info/WHEEL
meros-0.1.0.dist-info/top_level.txt
meros-0.1.0.dist-info/RECORD
