Metadata-Version: 2.1
Name: meros
Version: 0.1.0
Summary: Meta-Recognition Tools for Open-Set Recognition
Home-page: https://github.com/sfeilaryan/MeROS
Author: Ryan Sfeila
Author-email: ryansfeila@gmail.com
License: BSD-3-Clause
Platform: UNKNOWN
Requires-Python: >=3.8, <3.10
License-File: LICENSE
Requires-Dist: Cython
Requires-Dist: gapstatistics
Requires-Dist: joblib
Requires-Dist: libmr
Requires-Dist: numpy
Requires-Dist: scikit-learn
Requires-Dist: scipy
Requires-Dist: threadpoolctl
Requires-Dist: matplotlib
Requires-Dist: matplotlib-inline
Requires-Dist: setuptools
